Metadata-Version: 2.1
Name: civiproxy-logs2json
Version: 1.0.8
Summary: Translate a CiviProxy logfile into JSON format.
Author-email: Marc Michalsky <michalsky@forumZFD.de>
License: The MIT License (MIT)
Project-URL: Homepage, https://github.com/MarcMichalsky/civiproxy_logs2json
Keywords: civicrm,json,logs
Classifier: License :: OSI Approved :: MIT License
Classifier: Programming Language :: Python
Classifier: Programming Language :: Python :: 3
Requires-Python: >=3.5
Provides-Extra: dev
License-File: LICENSE
